archive_strategy/__init__.py
archive_strategy/archive_file.py
archive_strategy/archiver.py
archive_strategy/config.py
archive_strategy/console.py
archive_strategy/main.py
archive_strategy/policy.py
archive_strategy/timeframe.py
archive_strategy-0.1.4.1.dist-info/METADATA
archive_strategy-0.1.4.1.dist-info/WHEEL
archive_strategy-0.1.4.1.dist-info/entry_points.txt
archive_strategy-0.1.4.1.dist-info/RECORD
