Metadata-Version: 2.1
Name: archive-strategy
Version: 0.1.4.1
Summary: 
Author: Pieter Paulussen
Author-email: pieterpaulussen@code-source.be
Requires-Python: >=3.9,<4.0
Classifier: Programming Language :: Python :: 3
Classifier: Programming Language :: Python :: 3.9
Classifier: Programming Language :: Python :: 3.10
Classifier: Programming Language :: Python :: 3.11
Requires-Dist: click (>=8.1.7,<9.0.0)
Requires-Dist: python-dateutil (>=2.8.2,<3.0.0)
Requires-Dist: rich (>=13.6.0,<14.0.0)
